rpnpy/__init__.py
rpnpy/calculator.py
rpnpy/errors.py
rpnpy/functions.py
rpnpy/inspect.py
rpnpy/io.py
rpnpy/modifiers.py
rpnpy/readline.py
rpnpy/tui.py
rpnpy/utils.py
rpnpy/cli/__init__.py
rpnpy/cli/rpn.py
rpnpy-3.2.0.dist-info/METADATA
rpnpy-3.2.0.dist-info/WHEEL
rpnpy-3.2.0.dist-info/entry_points.txt
rpnpy-3.2.0.dist-info/licenses/AUTHORS.md
rpnpy-3.2.0.dist-info/RECORD
