Metadata-Version: 2.4
Name: rpnpy
Version: 3.2.0
Summary: Control an RPN calculator from Python.
Project-URL: Homepage, https://github.com/terrycojones/rpnpy
Project-URL: Repository, https://github.com/terrycojones/rpnpy
Project-URL: Download, https://github.com/terrycojones/rpnpy
Author-email: "Terry C. Jones" <terence.jones@charite.de>
License: MIT
License-File: AUTHORS.md
Keywords: TUI,calculator,polish,reverse,rpn
Classifier: Development Status :: 4 - Beta
Classifier: Intended Audience :: Developers
Classifier: License :: OSI Approved :: MIT License
Classifier: Operating System :: OS Independent
Classifier: Programming Language :: Python :: 3
Classifier: Programming Language :: Python :: 3.9
Classifier: Programming Language :: Python :: 3.10
Classifier: Programming Language :: Python :: 3.11
Classifier: Programming Language :: Python :: 3.12
Classifier: Programming Language :: Python :: 3.13
Classifier: Programming Language :: Python :: 3.14
Classifier: Topic :: Software Development :: Libraries :: Python Modules
Requires-Python: >=3.9
Requires-Dist: engineering-notation
Requires-Dist: gnureadline>=8.2.13
Requires-Dist: rich>=14.2.0
Requires-Dist: textual>=0.82.0
